[
  {
    "title": "",
    "description": "",
    "creator": "",
    "url": "https://images.pexels.com/photos/1066176/pexels-photo-1066176.jpeg?auto=compress&cs=tinysrgb&w=1200",
    "sociality": "new popular",
    "category": "photography",
    "tag": "",
    "medium": "photography"
  },
  {
    "title": "",
    "description": "",
    "creator": "",
    "url": "https://images.pexels.com/photos/1366630/pexels-photo-1366630.jpeg?auto=compress&cs=tinysrgb&w=1200",
    "sociality": "following popular",
    "category": "branding",
    "tag": "",
    "medium": "graphics"
  },
  {
    "title": "",
    "description": "",
    "creator": "",
    "url": "https://images.pexels.com/photos/800005/pexels-photo-800005.jpeg?auto=compress&cs=tinysrgb&w=1200",
    "sociality": "popular",
    "category": "social media",
    "tag": "",
    "medium": "photography"
  },
  {
    "title": "",
    "description": "",
    "creator": "",
    "url": "https://images.pexels.com/photos/2101187/pexels-photo-2101187.jpeg?auto=compress&cs=tinysrgb&w=1200",
    "sociality": "new",
    "category": "events",
    "tag": "",
    "medium": "multimedia"
  },
  {
    "title": "",
    "description": "",
    "creator": "",
    "url": "https://images.pexels.com/photos/1269968/pexels-photo-1269968.jpeg?auto=compress&cs=tinysrgb&w=1200",
    "sociality": "popular",
    "category": "events",
    "tag": "",
    "medium": "multimedia"
  },
  {
    "title": "",
    "description": "",
    "creator": "",
    "url": "https://images.pexels.com/photos/2318543/pexels-photo-2318543.jpeg?auto=compress&cs=tinysrgb&w=1200",
    "sociality": "popular",
    "category": "events",
    "tag": "",
    "medium": "multimedia"
  },
  {
    "title": "",
    "description": "",
    "creator": "",
    "url": "https://images.pexels.com/photos/1519088/pexels-photo-1519088.jpeg?auto=compress&cs=tinysrgb&w=1200",
    "sociality": "new following",
    "category": "events",
    "tag": "",
    "medium": "multimedia"
  },
  {
    "title": "",
    "description": "",
    "creator": "",
    "url": "https://images.pexels.com/photos/60597/dahlia-red-blossom-bloom-60597.jpeg?auto=compress&cs=tinysrgb&w=1200",
    "sociality": "new",
    "category": "events",
    "tag": "",
    "medium": "multimedia"
  },
  {
    "title": "",
    "description": "",
    "creator": "",
    "url": "https://images.pexels.com/photos/2874998/pexels-photo-2874998.jpeg?auto=compress&cs=tinysrgb&w=1200",
    "sociality": "popular following",
    "category": "events",
    "tag": "",
    "medium": "multimedia"
  },
  {
    "title": "",
    "description": "",
    "creator": "",
    "url": "https://images.pexels.com/photos/5876586/pexels-photo-5876586.jpeg?auto=compress&cs=tinysrgb&w=1200",
    "sociality": "new",
    "category": "events",
    "tag": "",
    "medium": "multimedia"
  },
  {
    "title": "",
    "description": "",
    "creator": "",
    "url": "https://images.pexels.com/photos/1029757/pexels-photo-1029757.jpeg?auto=compress&cs=tinysrgb&w=1200",
    "sociality": "popular",
    "category": "events",
    "tag": "",
    "medium": "multimedia"
  },
  {
    "title": "",
    "description": "",
    "creator": "",
    "url": "https://images.pexels.com/photos/607812/pexels-photo-607812.jpeg?auto=compress&cs=tinysrgb&w=1200",
    "sociality": "popular following",
    "category": "events",
    "tag": "",
    "medium": "multimedia"
  }
]